ubuntudesign/__init__.py
ubuntudesign_asset_mapper-0.10.dist-info/LICENSE.txt
ubuntudesign_asset_mapper-0.10.dist-info/METADATA
ubuntudesign_asset_mapper-0.10.dist-info/WHEEL
ubuntudesign_asset_mapper-0.10.dist-info/top_level.txt
ubuntudesign_asset_mapper-0.10.dist-info/RECORD
