Metadata-Version: 2.1
Name: ubuntudesign-asset-mapper
Version: 0.10
Summary: A mapping class for using the Ubuntu asset server.
Home-page: https://github.com/ubuntudesign/asset-mapper
Author: Robin
Author-email: robin.winslow@canonical.com
License: UNKNOWN
Platform: UNKNOWN
Requires-Dist: requests (>=2.0)
